lung_analysis_pipeline/__init__.py
lung_analysis_pipeline/model_pipeline.py
lung_analysis_pipeline/Feature_Extractor/__init__.py
lung_analysis_pipeline/Feature_Extractor/HSCNN/__init__.py
lung_analysis_pipeline/Feature_Extractor/HSCNN/dataloader.py
lung_analysis_pipeline/Feature_Extractor/HSCNN/model.py
lung_analysis_pipeline/Feature_Extractor/HSCNN/train.py
lung_analysis_pipeline/Feature_Extractor/radiomics/__init__.py
lung_analysis_pipeline/Feature_Extractor/radiomics/feature_extractor.py
lung_analysis_pipeline/NoduleDetect_SANet/__init__.py
lung_analysis_pipeline/NoduleDetect_SANet/config.py
lung_analysis_pipeline/NoduleDetect_SANet/evaluation_updt.py
lung_analysis_pipeline/NoduleDetect_SANet/test.py
lung_analysis_pipeline/NoduleDetect_SANet/test_normCnd.py
lung_analysis_pipeline/NoduleDetect_SANet/train.py
lung_analysis_pipeline/NoduleDetect_SANet/dataset/__init__.py
lung_analysis_pipeline/NoduleDetect_SANet/dataset/bbox_reader.py
lung_analysis_pipeline/NoduleDetect_SANet/dataset/bbox_reader_UCLA.py
lung_analysis_pipeline/NoduleDetect_SANet/dataset/collate.py
lung_analysis_pipeline/NoduleDetect_SANet/evaluationScript/NoduleFinding.py
lung_analysis_pipeline/NoduleDetect_SANet/evaluationScript/__init__.py
lung_analysis_pipeline/NoduleDetect_SANet/evaluationScript/noduleCADEvaluationLUNA16.py
lung_analysis_pipeline/NoduleDetect_SANet/evaluationScript/tools/__init__.py
lung_analysis_pipeline/NoduleDetect_SANet/evaluationScript/tools/csvTools.py
lung_analysis_pipeline/NoduleDetect_SANet/net/__init__.py
lung_analysis_pipeline/NoduleDetect_SANet/net/cgnl.py
lung_analysis_pipeline/NoduleDetect_SANet/net/resnet.py
lung_analysis_pipeline/NoduleDetect_SANet/net/sanet.py
lung_analysis_pipeline/NoduleDetect_SANet/net/layer/__init__.py
lung_analysis_pipeline/NoduleDetect_SANet/net/layer/rcnn_loss.py
lung_analysis_pipeline/NoduleDetect_SANet/net/layer/rcnn_nms.py
lung_analysis_pipeline/NoduleDetect_SANet/net/layer/rcnn_target.py
lung_analysis_pipeline-0.0.3.dist-info/METADATA
lung_analysis_pipeline-0.0.3.dist-info/WHEEL
lung_analysis_pipeline-0.0.3.dist-info/top_level.txt
lung_analysis_pipeline-0.0.3.dist-info/RECORD
